{"description":"Checking toEqual() method|Load the URL","passed":false,"pending":false,"os":"Windows NT","instanceId":12704,"browser":{"name":"chrome","version":"79.0.3945.88"},"message":["Expected 0 not to equal 0."],"trace":["Error: Failed expectation\n    at UserContext.<anonymous> (C:\\ProtractorAutomation\\TestScript\\TC01_Load&Validate_Page.js:62:40)\n    at C:\\Users\\Laptop\\AppData\\Roaming\\npm\\node_modules\\protractor\\node_modules\\jasminewd2\\index.js:112:25\n    at new ManagedPromise (C:\\Users\\Laptop\\AppData\\Roaming\\npm\\node_modules\\protractor\\node_modules\\selenium-webdriver\\lib\\promise.js:1077:7)\n    at ControlFlow.promise (C:\\Users\\Laptop\\AppData\\Roaming\\npm\\node_modules\\protractor\\node_modules\\selenium-webdriver\\lib\\promise.js:2505:12)\n    at schedulerExecute (C:\\Users\\Laptop\\AppData\\Roaming\\npm\\node_modules\\protractor\\node_modules\\jasminewd2\\index.js:95:18)\n    at TaskQueue.execute_ (C:\\Users\\Laptop\\AppData\\Roaming\\npm\\node_modules\\protractor\\node_modules\\selenium-webdriver\\lib\\promise.js:3084:14)\n    at TaskQueue.executeNext_ (C:\\Users\\Laptop\\AppData\\Roaming\\npm\\node_modules\\protractor\\node_modules\\selenium-webdriver\\lib\\promise.js:3067:27)\n    at asyncRun (C:\\Users\\Laptop\\AppData\\Roaming\\npm\\node_modules\\protractor\\node_modules\\selenium-webdriver\\lib\\promise.js:2974:25)\n    at C:\\Users\\Laptop\\AppData\\Roaming\\npm\\node_modules\\protractor\\node_modules\\selenium-webdriver\\lib\\promise.js:668:7"],"browserLogs":[],"screenShotFile":"008900fd-0066-00a2-00c4-000c00070022.png","timestamp":1579234139645,"duration":23}
